{
  "products": [
    {
      "id": 1,
      "name": "Bread Fig And Almond",
      "price": 88.27
    },
    {
      "id": 2,
      "name": "Mussels - Cultivated",
      "price": 81.4
    },
    {
      "id": 3,
      "name": "Roe - Flying Fish",
      "price": 77.07
    },
    {
      "id": 4,
      "name": "Gatorade - Lemon Lime",
      "price": 95.18
    },
    {
      "id": 5,
      "name": "Port - 74 Brights",
      "price": 6.3
    },
    {
      "id": 6,
      "name": "Steam Pan - Half Size Deep",
      "price": 11.43
    },
    {
      "id": 7,
      "name": "Bread Base - Goodhearth",
      "price": 46.66
    },
    {
      "id": 8,
      "name": "Bread Bowl Plain",
      "price": 63.66
    },
    {
      "id": 9,
      "name": "Rum - Coconut, Malibu",
      "price": 68.86
    },
    {
      "id": 10,
      "name": "Beef - Salted",
      "price": 65.02
    },
    {
      "id": 11,
      "name": "Liqueur - Melon",
      "price": 76.71
    },
    {
      "id": 12,
      "name": "Lemonade - Pineapple Passion",
      "price": 40.92
    },
    {
      "id": 13,
      "name": "Tea - Decaf 1 Cup",
      "price": 69.06
    },
    {
      "id": 14,
      "name": "Daikon Radish",
      "price": 68.14
    },
    {
      "id": 15,
      "name": "Squash - Sunburst",
      "price": 16.53
    },
    {
      "id": 16,
      "name": "Ocean Spray - Kiwi Strawberry",
      "price": 65.67
    },
    {
      "id": 17,
      "name": "Bread - Calabrese Baguette",
      "price": 20.11
    },
    {
      "id": 18,
      "name": "Pork - Smoked Kassler",
      "price": 41.01
    },
    {
      "id": 19,
      "name": "Beer - Mill St Organic",
      "price": 20.98
    },
    {
      "id": 20,
      "name": "Apron",
      "price": 34.59
    },
    {
      "id": 21,
      "name": "Corn Kernels - Frozen",
      "price": 52.18
    },
    {
      "id": 22,
      "name": "Mortadella",
      "price": 7.4
    },
    {
      "id": 23,
      "name": "Melon - Watermelon, Seedless",
      "price": 32.14
    },
    {
      "id": 24,
      "name": "Beef - Flank Steak",
      "price": 87.2
    },
    {
      "id": 25,
      "name": "Pate - Peppercorn",
      "price": 35.43
    },
    {
      "id": 26,
      "name": "Beans - Long, Chinese",
      "price": 69.22
    },
    {
      "id": 27,
      "name": "Coffee Guatemala Dark",
      "price": 74.96
    },
    {
      "id": 28,
      "name": "Ice Cream Bar - Hageen Daz To",
      "price": 54.21
    },
    {
      "id": 29,
      "name": "Wine - Pinot Grigio Collavini",
      "price": 43.17
    },
    {
      "id": 30,
      "name": "Nestea - Ice Tea, Diet",
      "price": 96.65
    },
    {
      "id": 31,
      "name": "Soup - Campbells Beef Noodle",
      "price": 76.74
    },
    {
      "id": 32,
      "name": "Basil - Dry, Rubbed",
      "price": 54.78
    },
    {
      "id": 33,
      "name": "Blouse / Shirt / Sweater",
      "price": 74.46
    },
    {
      "id": 34,
      "name": "Red Snapper - Fillet, Skin On",
      "price": 17.87
    },
    {
      "id": 35,
      "name": "Soho Lychee Liqueur",
      "price": 41.07
    },
    {
      "id": 36,
      "name": "Pants Custom Dry Clean",
      "price": 64.97
    },
    {
      "id": 37,
      "name": "Bagel - Whole White Sesame",
      "price": 87.11
    },
    {
      "id": 38,
      "name": "Island Oasis - Peach Daiquiri",
      "price": 86.4
    },
    {
      "id": 39,
      "name": "Mussels - Cultivated",
      "price": 77.3
    },
    {
      "id": 40,
      "name": "Garam Marsala",
      "price": 72.1
    },
    {
      "id": 41,
      "name": "Syrup - Monin, Swiss Choclate",
      "price": 40.42
    },
    {
      "id": 42,
      "name": "Lid Tray - 12in Dome",
      "price": 80.11
    },
    {
      "id": 43,
      "name": "Mangoes",
      "price": 68.11
    },
    {
      "id": 44,
      "name": "Fish - Base, Bouillion",
      "price": 86.07
    },
    {
      "id": 45,
      "name": "Sherry - Dry",
      "price": 99.4
    },
    {
      "id": 46,
      "name": "Horseradish - Prepared",
      "price": 84.81
    },
    {
      "id": 47,
      "name": "Snapple Lemon Tea",
      "price": 89.67
    },
    {
      "id": 48,
      "name": "Pork - Ham, Virginia",
      "price": 78.78
    },
    {
      "id": 49,
      "name": "Capicola - Hot",
      "price": 99.03
    },
    {
      "id": 50,
      "name": "Ecolab - Mikroklene 4/4 L",
      "price": 81.03
    },
    {
      "id": 51,
      "name": "Noodles - Steamed Chow Mein",
      "price": 31.58
    },
    {
      "id": 52,
      "name": "Coconut - Shredded, Sweet",
      "price": 87.17
    },
    {
      "id": 53,
      "name": "Campari",
      "price": 19.54
    },
    {
      "id": 54,
      "name": "Spice - Onion Powder Granulated",
      "price": 12.07
    },
    {
      "id": 55,
      "name": "Shallots",
      "price": 37.42
    },
    {
      "id": 56,
      "name": "Wine - Pinot Noir Mondavi Coastal",
      "price": 11.7
    },
    {
      "id": 57,
      "name": "Salmon - Fillets",
      "price": 31.96
    },
    {
      "id": 58,
      "name": "Star Anise, Whole",
      "price": 10.02
    },
    {
      "id": 59,
      "name": "Hand Towel",
      "price": 76.97
    },
    {
      "id": 60,
      "name": "Piping Jelly - All Colours",
      "price": 18.22
    },
    {
      "id": 61,
      "name": "The Pop Shoppe - Root Beer",
      "price": 93.88
    },
    {
      "id": 62,
      "name": "Red Snapper - Fillet, Skin On",
      "price": 63.93
    },
    {
      "id": 63,
      "name": "Hot Choc Vending",
      "price": 15.53
    },
    {
      "id": 64,
      "name": "Cheese - Brie, Triple Creme",
      "price": 39.18
    },
    {
      "id": 65,
      "name": "Wine - Red Oakridge Merlot",
      "price": 59.22
    },
    {
      "id": 66,
      "name": "Ginsing - Fresh",
      "price": 63.84
    },
    {
      "id": 67,
      "name": "Wine - Cousino Macul Antiguas",
      "price": 42.29
    },
    {
      "id": 68,
      "name": "Wine - Chardonnay Mondavi",
      "price": 1.39
    },
    {
      "id": 69,
      "name": "Syrup - Pancake",
      "price": 78.42
    },
    {
      "id": 70,
      "name": "Gelatine Leaves - Envelopes",
      "price": 62.72
    },
    {
      "id": 71,
      "name": "Basil - Thai",
      "price": 46.71
    },
    {
      "id": 72,
      "name": "Arctic Char - Fillets",
      "price": 4.76
    },
    {
      "id": 73,
      "name": "Chocolate - Liqueur Cups With Foil",
      "price": 54.33
    },
    {
      "id": 74,
      "name": "Veal - Eye Of Round",
      "price": 30.52
    },
    {
      "id": 75,
      "name": "Tea - Darjeeling, Azzura",
      "price": 91.89
    },
    {
      "id": 76,
      "name": "Apple - Granny Smith",
      "price": 2.33
    },
    {
      "id": 77,
      "name": "Cheese - Pied De Vents",
      "price": 83.12
    },
    {
      "id": 78,
      "name": "Wine - Riesling Dr. Pauly",
      "price": 46.74
    },
    {
      "id": 79,
      "name": "Bread - Olive Dinner Roll",
      "price": 55.64
    },
    {
      "id": 80,
      "name": "Wine - Malbec Trapiche Reserve",
      "price": 12.24
    },
    {
      "id": 81,
      "name": "Sausage - Chorizo",
      "price": 48.59
    },
    {
      "id": 82,
      "name": "Island Oasis - Pina Colada",
      "price": 93.71
    },
    {
      "id": 83,
      "name": "Milk Powder",
      "price": 4.96
    },
    {
      "id": 84,
      "name": "Wine - Pinot Noir Latour",
      "price": 49.55
    },
    {
      "id": 85,
      "name": "Squash - Sunburst",
      "price": 76.96
    },
    {
      "id": 86,
      "name": "Cookie Dough - Double",
      "price": 98.82
    },
    {
      "id": 87,
      "name": "Ice Cream - Life Savers",
      "price": 67.27
    },
    {
      "id": 88,
      "name": "Sobe - Green Tea",
      "price": 40.55
    },
    {
      "id": 89,
      "name": "Lamb - Leg, Bone In",
      "price": 8.72
    },
    {
      "id": 90,
      "name": "Cinnamon - Ground",
      "price": 99.23
    },
    {
      "id": 91,
      "name": "Bread - Onion Focaccia",
      "price": 48.01
    },
    {
      "id": 92,
      "name": "Lamb - Whole, Frozen",
      "price": 15.02
    },
    {
      "id": 93,
      "name": "Bread - Hamburger Buns",
      "price": 60.67
    },
    {
      "id": 94,
      "name": "Cheese - Blue",
      "price": 88.0
    },
    {
      "id": 95,
      "name": "Chocolate - Unsweetened",
      "price": 34.16
    },
    {
      "id": 96,
      "name": "Table Cloth 81x81 White",
      "price": 93.1
    },
    {
      "id": 97,
      "name": "Plums - Red",
      "price": 19.45
    },
    {
      "id": 98,
      "name": "Lettuce - Lambs Mash",
      "price": 61.74
    },
    {
      "id": 99,
      "name": "Shiratamako - Rice Flour",
      "price": 65.25
    },
    {
      "id": 100,
      "name": "Lettuce - Lolla Rosa",
      "price": 68.46
    }
  ]
}
